indigetranslate_api/__init__.py
indigetranslate_api/client.py
indigetranslate_api-1.0.2.dist-info/METADATA
indigetranslate_api-1.0.2.dist-info/WHEEL
indigetranslate_api-1.0.2.dist-info/top_level.txt
indigetranslate_api-1.0.2.dist-info/RECORD
