Metadata-Version: 2.4
Name: indigetranslate-api
Version: 1.0.2
Summary: API Oficial de IndigeTranslate para traducciones de lenguas indígenas.
Author: WinCreativeX
License: MIT
Project-URL: Homepage, https://wincreativex.vercel.app
Project-URL: Documentation, https://wincreativex.vercel.app/api-docs
Requires-Dist: requests
